lambda_monitoring/__init__.py
m4rkw_lambda_tracing-0.0.77.dist-info/licenses/LICENSE
m4rkw_lambda_tracing-0.0.77.dist-info/METADATA
m4rkw_lambda_tracing-0.0.77.dist-info/WHEEL
m4rkw_lambda_tracing-0.0.77.dist-info/top_level.txt
m4rkw_lambda_tracing-0.0.77.dist-info/RECORD
