Metadata-Version: 2.4
Name: m4rkw-lambda-tracing
Version: 0.0.77
Summary: lambda monitoring
Author-email: Your Name <your@email.com>
License: MIT License
License-File: LICENSE
Requires-Dist: boto3
Requires-Dist: python-pushover2
Requires-Dist: requests
Requires-Dist: requests[socks]
Requires-Dist: PySocks
Dynamic: license-file
